MANIFEST.in
README.md
VERSION
setup.py
nefertari_guards/__init__.py
nefertari_guards/acl.py
nefertari_guards/acl_utils.py
nefertari_guards/base.py
nefertari_guards/documents.py
nefertari_guards/elasticsearch.py
nefertari_guards/engine.py
nefertari_guards/nefertari_mongodb.py
nefertari_guards/nefertari_sqla.py
nefertari_guards/view.py
nefertari_guards.egg-info/PKG-INFO
nefertari_guards.egg-info/SOURCES.txt
nefertari_guards.egg-info/dependency_links.txt
nefertari_guards.egg-info/entry_points.txt
nefertari_guards.egg-info/not-zip-safe
nefertari_guards.egg-info/pbr.json
nefertari_guards.egg-info/requires.txt
nefertari_guards.egg-info/top_level.txt
nefertari_guards/scripts/__init__.py
nefertari_guards/scripts/count_ace.py
nefertari_guards/scripts/script_utils.py
nefertari_guards/scripts/update_ace.py
tests/__init__.py
tests/test_acl_utils.py
tests/test_base.py
tests/test_count_ace_script.py
tests/test_documents.py
tests/test_elasticsearch.py
tests/test_nefertari_sqla.py
tests/test_script_utils.py
tests/test_update_ace_script.py
tests/test_view.py