Metadata-Version: 1.1
Name: nefertari-guards
Version: 0.2.0
Summary: Advanced ACLs for Nefertari
Home-page: https://github.com/ramses-tech/nefertari-guards
Author: Ramses
Author-email: hello@ramses.tech
License: UNKNOWN
Keywords: web pyramid pylons nefertari acl
Platform: UNKNOWN
Classifier: Programming Language :: Python
Classifier: Programming Language :: Python :: 2
Classifier: Programming Language :: Python :: 2.7
Classifier: Programming Language :: Python :: 3
Classifier: Programming Language :: Python :: 3.4
Classifier: Programming Language :: Python :: 3.5
Classifier: Framework :: Pyramid
Classifier: Topic :: Internet :: WWW/HTTP
Classifier: Topic :: Internet :: WWW/HTTP :: WSGI :: Application
